iChingX-0.0.79.dist-info/WHEEL
iChingX-0.0.79.dist-info/entry_points.txt
iChingX-0.0.79.dist-info/METADATA
iChingX-0.0.79.dist-info/RECORD
iChingX-0.0.79.dist-info/top_level.txt
iChingX/__init__.py
iChingX/helper/_human.cpython-38-x86_64-linux-gnu.so
iChingX/helper/_cache.cpython-38-x86_64-linux-gnu.so
iChingX/helper/_config.cpython-38-x86_64-linux-gnu.so
iChingX/helper/__init__.py
iChingX/helper/_hash.cpython-38-x86_64-linux-gnu.so
iChingX/helper/_env.cpython-38-x86_64-linux-gnu.so
iChingX/helper/_str.cpython-38-x86_64-linux-gnu.so
iChingX/helper/_log.cpython-38-x86_64-linux-gnu.so
iChingX/helper/_utils.cpython-38-x86_64-linux-gnu.so
iChingX/helper/_json.cpython-38-x86_64-linux-gnu.so
iChingX/helper/_crypt.cpython-38-x86_64-linux-gnu.so
iChingX/helper/_loader.cpython-38-x86_64-linux-gnu.so
iChingX/helper/_date.cpython-38-x86_64-linux-gnu.so
iChingX/helper/_arr.cpython-38-x86_64-linux-gnu.so
iChingX/helper/cache_driver/__init__.py
iChingX/helper/cache_driver/file_driver.cpython-38-x86_64-linux-gnu.so
iChingX/helper/cache_driver/mysql_driver.cpython-38-x86_64-linux-gnu.so
iChingX/helper/cache_driver/redis_driver.cpython-38-x86_64-linux-gnu.so
iChingX/helper/cache_driver/cache_interface.cpython-38-x86_64-linux-gnu.so
iChingX/helper/cache_driver/tag_set.cpython-38-x86_64-linux-gnu.so
iChingX/helper/cache_driver/sqlite_driver.cpython-38-x86_64-linux-gnu.so
iChingX/helper/cache_driver/memory_driver.cpython-38-x86_64-linux-gnu.so
iChingX/bin/_envinfo.cpython-38-x86_64-linux-gnu.so
iChingX/bin/iching.cpython-38-x86_64-linux-gnu.so
iChingX/bin/__init__.py
iChingX/bin/_build.cpython-38-x86_64-linux-gnu.so
iChingX/bin/_setup.cpython-38-x86_64-linux-gnu.so
iChingX/database/constants.cpython-38-x86_64-linux-gnu.so
iChingX/database/__init__.py
iChingX/database/db_manager.cpython-38-x86_64-linux-gnu.so
iChingX/database/db_manager.py
iChingX/database/builder/mysql_builder.cpython-38-x86_64-linux-gnu.so
iChingX/database/builder/__init__.py
iChingX/database/builder/base_builder.cpython-38-x86_64-linux-gnu.so
iChingX/database/builder/sqlite_builder.cpython-38-x86_64-linux-gnu.so
iChingX/database/query/raw.py
